.coveragerc
CHANGE.rst
MANIFEST.in
README.rst
setup.py
dmu_utils/__init__.py
dmu_utils/collections.py
dmu_utils/misc.py
dmu_utils/pkg_resources.py
dmu_utils.egg-info/PKG-INFO
dmu_utils.egg-info/SOURCES.txt
dmu_utils.egg-info/dependency_links.txt
dmu_utils.egg-info/not-zip-safe
dmu_utils.egg-info/requires.txt
dmu_utils.egg-info/top_level.txt
dmu_utils/configuration/__init__.py
dmu_utils/configuration/base.py
dmu_utils/logging/__init__.py
dmu_utils/logging/duration.py
dmu_utils/schematics/__init__.py
dmu_utils/schematics/models.py
dmu_utils/schematics/types.py
dmu_utils/sqlachemy/__init__.py
dmu_utils/sqlachemy/models.py
dmu_utils/sqlachemy/session.py
dmu_utils/sqlachemy/types.py
dmu_utils/tests/__init__.py
dmu_utils/tests/test_misc.py
dmu_utils/tests/logging/__init__.py
dmu_utils/tests/logging/test_duration.py