Metadata-Version: 1.1
Name: dmu-utils
Version: 0.0.3
Summary: DMU Utils
Home-page: https://github.com/dmugtasimov/dmu-utils
Author: Dmitry Mugtasimov
Author-email: dmugtasimov@gmail.com
License: UNKNOWN
Platform: any
Classifier: Development Status :: 2 - Pre-Alpha
Classifier: Intended Audience :: Developers
Classifier: Natural Language :: English
Classifier: Programming Language :: Python :: 2
Classifier: Programming Language :: Python :: 2.7
